nbdev_template/__init__.py
nbdev_template/_nbdev.py
nbdev_template/inventory.py
villaInventorySdk/__init__.py
villaInventorySdk/_nbdev.py
villaInventorySdk/inventory.py
villaWalletDatabase/__init__.py
villaWalletDatabase/_nbdev.py
villaWalletDatabase/database.py
villaWalletDatabase-0.0.3.dist-info/LICENSE
villaWalletDatabase-0.0.3.dist-info/METADATA
villaWalletDatabase-0.0.3.dist-info/WHEEL
villaWalletDatabase-0.0.3.dist-info/entry_points.txt
villaWalletDatabase-0.0.3.dist-info/top_level.txt
villaWalletDatabase-0.0.3.dist-info/RECORD
